{
    "customers": [
      {
        "id": 1,
        "name": "Jordan Stevenson",
        "email": "dayna19@yahoo.com",
        "customerId": "#345889",
        "country": "United States",
        "countryFlag": "https://flagcdn.com/w40/us.png",
        "orders": 41,
        "totalSpent": "$32,907",
        "avatar": "https://randomuser.me/api/portraits/men/1.jpg"
      },
      {
        "id": 2,
        "name": "Benedetto Rossiter",
        "email": "lorena@yahoo.com",
        "customerId": "#234875",
        "country": "Brazil",
        "countryFlag": "https://flagcdn.com/w40/br.png",
        "orders": 12,
        "totalSpent": "$5,347",
        "avatar": "https://randomuser.me/api/portraits/men/2.jpg"
      },
      {
        "id": 3,
        "name": "Bentlee Emblin",
        "email": "bemblinF@gmail.com",
        "customerId": "#783645",
        "country": "India",
        "countryFlag": "https://flagcdn.com/w40/in.png",
        "orders": 36,
        "totalSpent": "$12,458",
        "avatar": "https://randomuser.me/api/portraits/men/3.jpg"
      },
      {
        "id": 4,
        "name": "Bertha Biner",
        "email": "bbinerH@gmail.com",
        "customerId": "#234876",
        "country": "Australia",
        "countryFlag": "https://flagcdn.com/w40/au.png",
        "orders": 7,
        "totalSpent": "$1,345",
        "avatar": "https://randomuser.me/api/portraits/women/1.jpg"
      },
      {
        "id": 5,
        "name": "Beverlie Krabbe",
        "email": "bkrabbe1d@gmail.com",
        "customerId": "#234598",
        "country": "France",
        "countryFlag": "https://flagcdn.com/w40/fr.png",
        "orders": 34,
        "totalSpent": "$24,435",
        "avatar": "https://randomuser.me/api/portraits/women/2.jpg"
      },
      {
        "id": 6,
        "name": "Beverlie Krabbe",
        "email": "bkrabbe1d@gmail.com",
        "customerId": "#234598",
        "country": "France",
        "countryFlag": "https://flagcdn.com/w40/fr.png",
        "orders": 34,
        "totalSpent": "$24,435",
        "avatar": "https://randomuser.me/api/portraits/women/2.jpg"
      }
    ]
  }
  